PRIVATE/changelog/PRIVATE_verify_fixes.py
PRIVATE/scripts/check_indexes.py
PRIVATE/scripts/check_local_llm_configs.py
PRIVATE/scripts/coverage_analyze.py
PRIVATE/scripts/data_consistency.py
PRIVATE/scripts/delete_memory.py
PRIVATE/scripts/dump_index_info.py
PRIVATE/scripts/dump_memory_keys.py
PRIVATE/scripts/find_join_memory.py
PRIVATE/scripts/find_memory_hits.py
PRIVATE/scripts/fix_local_llm_configs.py
PRIVATE/scripts/maintain_docs.py
PRIVATE/scripts/migrate_to_redisstack.py
PRIVATE/scripts/migrate_to_schemas.py
PRIVATE/scripts/orka_cleanup.py
PRIVATE/scripts/parse_trace_example.py
PRIVATE/scripts/run_all_examples.py
PRIVATE/scripts/search_index.py
PRIVATE/scripts/test_mock_audit.py
PRIVATE/scripts/update_headers.py
PRIVATE/scripts/with_cleanup.py
docs/benchmark/run_benchmark.py
docs/expSOC01/images/generate_chart_images.py
docs/exp_local_SOC-02/CSV/extract_comprehensive_enhanced.py
docs/exp_local_SOC-02/CSV/extract_comprehensive_generic.py
docs/exp_local_SOC-02/CSV/extract_csv.py
docs/sphinx/build_docs.py
docs/sphinx/conf.py
examples/PRIVATE_exp01/organize_experiment_logs.py
examples/PRIVATE_exp01/run_cognitive_iteration.py
examples/PRIVATE_exp01/run_cognitive_iteration_100.py
logs/analyze_traces.py
orka/__init__.py
orka/contracts.py
orka/fork_group_manager.py
orka/loader.py
orka/memory_logger.py
orka/orchestrator.py
orka/orchestrator_error_wrapper.py
orka/orka_cli.py
orka/orka_start.py
orka/registry.py
orka/response_builder.py
orka/server.py
orka/tui_interface.py
orka/agents/__init__.py
orka/agents/agents.py
orka/agents/base_agent.py
orka/agents/invariant_validator_agent.py
orka/agents/llm_agents.py
orka/agents/local_cost_calculator.py
orka/agents/local_llm_agents.py
orka/agents/validation_and_structuring_agent.py
orka/agents/plan_validator/__init__.py
orka/agents/plan_validator/agent.py
orka/agents/plan_validator/boolean_parser.py
orka/agents/plan_validator/critique_parser.py
orka/agents/plan_validator/llm_client.py
orka/agents/plan_validator/prompt_builder.py
orka_reasoning-0.9.14.dist-info/licenses/LICENSE
orka_reasoning-0.9.14.dist-info/METADATA
orka_reasoning-0.9.14.dist-info/WHEEL
orka_reasoning-0.9.14.dist-info/entry_points.txt
orka_reasoning-0.9.14.dist-info/top_level.txt
orka_reasoning-0.9.14.dist-info/RECORD
