Metadata-Version: 2.4
Name: orka-reasoning
Version: 0.9.14
Summary: Modular agent orchestrator for reasoning pipelines
Author-email: Marco Somma <marcosomma.work@gmail.com>
License-Expression: Apache-2.0
Project-URL: Homepage, https://orkacore.com
Project-URL: Documentation, https://docs.orkacore.com
Project-URL: Repository, https://github.com/marcosomma/orka-reasoning
Classifier: Programming Language :: Python :: 3
Classifier: Operating System :: OS Independent
Classifier: Development Status :: 4 - Beta
Classifier: Intended Audience :: Developers
Classifier: Topic :: Software Development :: Libraries :: Python Modules
Requires-Python: >=3.11
License-File: LICENSE
Requires-Dist: redis[async,search]==4.5.5
Requires-Dist: redis-om==0.3.5
Requires-Dist: rmtest>=0.7.0
Requires-Dist: pyyaml>=6.0.2
Requires-Dist: python-dotenv>=0.19.0
Requires-Dist: GPUtil>=1.4.0
Requires-Dist: psutil>=7.0.0
Requires-Dist: click<9.0.0,>=8.1.8
Requires-Dist: openai>=1.0.0
Requires-Dist: litellm>=1.0.0
Requires-Dist: numpy>=2.3.1
Requires-Dist: sentence_transformers>=5.0.0
Requires-Dist: ddgs>=3.0.0
Requires-Dist: fastapi>=0.68.0
Requires-Dist: uvicorn>=0.15.0
Requires-Dist: pydantic>=1.8.0
Requires-Dist: httpx>=0.24.0
Requires-Dist: jinja2>=3.0.0
Requires-Dist: async-timeout>=4.0.0
Requires-Dist: json-repair>=0.25.0
Requires-Dist: jsonschema>=4.20.0
Requires-Dist: rich>=13.0.0
Requires-Dist: textual>=0.40.0
Provides-Extra: dev
Requires-Dist: pytest>=7.0.0; extra == "dev"
Requires-Dist: pytest-asyncio>=0.21.0; extra == "dev"
Requires-Dist: pytest-cov>=4.0.0; extra == "dev"
Requires-Dist: coverage>=7.0.0; extra == "dev"
Requires-Dist: fakeredis>=2.0.0; extra == "dev"
Requires-Dist: black>=24.2.0; extra == "dev"
Requires-Dist: flake8>=7.0.0; extra == "dev"
Requires-Dist: flake8-docstrings>=1.7.0; extra == "dev"
Requires-Dist: flake8-bugbear>=24.1.0; extra == "dev"
Requires-Dist: flake8-comprehensions>=3.14.0; extra == "dev"
Requires-Dist: flake8-pytest-style>=1.7.0; extra == "dev"
Requires-Dist: mypy>=1.17.0; extra == "dev"
Requires-Dist: types-redis>=4.2.0; extra == "dev"
Requires-Dist: types-PyYAML>=6.0.12; extra == "dev"
Requires-Dist: types-requests>=2.32.0; extra == "dev"
Requires-Dist: types-psutil>=7.0.0; extra == "dev"
Requires-Dist: sphinx>=7.0.0; extra == "dev"
Requires-Dist: sphinx-rtd-theme>=1.0.0; extra == "dev"
Provides-Extra: extra
Provides-Extra: prod
Requires-Dist: gunicorn>=21.0.0; extra == "prod"
Requires-Dist: supervisor>=4.2.0; extra == "prod"
Provides-Extra: ml
Requires-Dist: sentence-transformers>=2.2.0; extra == "ml"
Requires-Dist: numpy>=1.21.0; extra == "ml"
Provides-Extra: all
Requires-Dist: orka-reasoning[dev,ml,prod,schema]; extra == "all"
Dynamic: license-file
